SimpleMqtt/AbstractSimpleMqtt.py
SimpleMqtt/DualContextCallback.py
SimpleMqtt/EventData.py
SimpleMqtt/SimpleMqttAsync.py
SimpleMqtt/SimpleMqttSync.py
SimpleMqtt/TopicCallback.py
SimpleMqtt/__init__.py
SimpleMqtt/py.typed
SimpleMqtt/utils.py
ki2_simple_mqtt-0.1.2.dist-info/LICENSE
ki2_simple_mqtt-0.1.2.dist-info/METADATA
ki2_simple_mqtt-0.1.2.dist-info/WHEEL
ki2_simple_mqtt-0.1.2.dist-info/RECORD
