Metadata-Version: 2.1
Name: ki2-simple-mqtt
Version: 0.1.2
Summary: SimpleMqtt is a Python library designed to simplify MQTT client operations. It extends the Paho MQTT client to provide enhanced functionality while maintaining a clean and flexible interface. Whether you're building synchronous or asynchronous applications, SimpleMqtt has you covered.
Home-page: https://gitlab.com/ki2-open/python/simple-mqtt
License: MIT
Author: Adrien KERFOURN
Author-email: ak.sitecontact@gmail.com
Requires-Python: >=3.10,<4.0
Classifier: License :: OSI Approved :: MIT License
Classifier: Programming Language :: Python :: 3
Classifier: Programming Language :: Python :: 3.10
Classifier: Programming Language :: Python :: 3.11
Classifier: Programming Language :: Python :: 3.12
Classifier: Programming Language :: Python :: 3.13
Requires-Dist: ki2-python-utils (>=0.3.5,<0.4.0)
Requires-Dist: paho-mqtt (>=2.1.0,<3.0.0)
Requires-Dist: typing-extensions (>=4.12.2,<5.0.0)
Project-URL: Repository, https://gitlab.com/ki2-open/python/simple-mqtt
